setup.py
ebb/__init__.py
ebb/__version__.py
ebb/constants.py
ebb/tests.py
ebb/units.py
ebb.egg-info/PKG-INFO
ebb.egg-info/SOURCES.txt
ebb.egg-info/dependency_links.txt
ebb.egg-info/entry_points.txt
ebb.egg-info/top_level.txt
ebb/fluids/Air.py
ebb/fluids/Fluid.py
ebb/fluids/Gas.py
ebb/fluids/Helium.py
ebb/fluids/Liquid.py
ebb/fluids/Nitrogen.py
ebb/fluids/Oxygen.py
ebb/fluids/Water.py
ebb/fluids/__init__.py
ebb/pipes/CircularPipe.py
ebb/pipes/Orifice.py
ebb/pipes/Pipe.py
ebb/pipes/RectangularPipe.py
ebb/pipes/__init__.py