Metadata-Version: 1.1
Name: ebb
Version: 0.0.5
Summary: A package for liquid flow calculations.
Home-page: http://lewisamarshall.github.io/ebb/
Author: Lewis A. Marshall
Author-email: lewis.a.marshall@gmail.com
License: LICENSE
Platform: UNKNOWN
Classifier: Programming Language :: Python
Classifier: Environment :: Console
Classifier: Intended Audience :: Science/Research
Classifier: Topic :: Software Development :: Libraries :: Python Modules
Requires: numpy
Requires: scipy
Requires: pint
Requires: click
